{
  "Beirut": ["Urban", "Cultural", "Historical Sites", "Beaches", "Pigeon Rocks", "Markets"],
  "Tripoli": ["Urban", "Cultural", "Historical Sites", "Castles", "Souks", "Harbours"],
  "Sidon": ["Urban", "Cultural", "Historical Sites", "Castles", "Sea Castle", "Old Souk"],
  "Baalbek": ["Cultural", "Historical Sites", "Roman Ruins", "Temples", "Mountains", "Archaeological Sites"],
  "Tyre": ["Urban", "Cultural", "Historical Sites", "Beaches", "Hippodrome", "UNESCO Sites"],
  "Nabatieh": ["Urban", "Cultural", "Historical Sites", "Mountains", "Shrine", "Markets"],
  "Jounieh": ["Urban", "Cultural", "Beaches", "Cable Cars", "Nightlife", "Teleferique"],
  "Aley": ["Urban", "Cultural", "Mountains", "Parks", "Resorts", "Pine Forests"],
  "Zahle": ["Urban", "Cultural", "Rivers", "Vineyards", "Wine Festivals", "Canyons"],
  "Zgharta-Ehden": ["Cultural", "Historical Sites", "Mountains", "Cedar Forests", "Nature Reserves", "Skiing"],
  "Byblos": ["Cultural", "Historical Sites", "Beaches", "Ancient Port", "Crusader Castle", "UNESCO Sites"],
  "Batroun": ["Urban", "Cultural", "Beaches", "Roman Ruins", "Wine Region", "Phoenician Walls"],
  "Mazraa": ["Urban", "Cultural", "Markets", "Parks", "Residential", "Commercial"],
  "Mousaitbeh": ["Urban", "Cultural", "Markets", "Parks", "Residential", "Commercial"],
  "Bachoura": ["Urban", "Cultural", "Markets", "Parks", "Residential", "Commercial"],
  "Achrafieh": ["Urban", "Cultural", "Historical Sites", "Parks", "Churches", "Embassies"],
  "Zuqaq al-Blat": ["Urban", "Cultural", "Markets", "Parks", "Residential", "Commercial"],
  "Medawar": ["Urban", "Cultural", "Markets", "Parks", "Residential", "Commercial"],
  "Ras Beirut": ["Urban", "Cultural", "Beaches", "Parks", "Universities", "Nightlife"],
  "Rmeil": ["Urban", "Cultural", "Markets", "Parks", "Residential", "Commercial"],
  "Minet el-Hosn": ["Urban", "Cultural", "Harbour", "Parks", "Hotels", "Waterfront"],
  "Dar el-Mraisseh": ["Urban", "Cultural", "Beaches", "Parks", "Corniche", "Restaurants"],
  "Marfa": ["Urban", "Cultural", "Port", "Markets", "Warehouses", "Commercial"],
  "Saifi": ["Urban", "Cultural", "Historical Sites", "Parks", "Villages", "Embassies"]
}