{
  "Lima": ["Urban", "Cultural", "Historical Sites", "Coastal", "Markets", "Museums"],
  "Arequipa": ["Urban", "Cultural", "Historical Sites", "Volcanoes", "Markets", "Cathedrals"],
  "Trujillo": ["Urban", "Cultural", "Historical Sites", "Archaeological Sites", "Beaches", "Markets"],
  "Chiclayo": ["Urban", "Cultural", "Historical Sites", "Markets", "Museums", "Tombs"],
  "Piura": ["Urban", "Coastal", "Historical Sites", "Markets", "Beaches", "Rivers"],
  "Iquitos": ["Urban", "Rivers", "Jungle", "Markets", "Biodiversity", "Boats"],
  "Cusco": ["Urban", "Cultural", "Historical Sites", "Mountains", "Inca Ruins", "Markets"],
  "Huancayo": ["Urban", "Cultural", "Markets", "Mountains", "Festivals", "Railways"],
  "Chimbote": ["Urban", "Coastal", "Ports", "Markets", "Fishing", "Beaches"],
  "Huánuco": ["Urban", "Rivers", "Historical Sites", "Markets", "Agriculture", "Canyons"],
  "Pucallpa": ["Urban", "Rivers", "Jungle", "Markets", "Forests", "Oil"],
  "Sullana": ["Urban", "Rivers", "Agricultural Areas", "Markets", "Valleys", "Irrigation"],
  "Tacna": ["Urban", "Cultural", "Historical Sites", "Markets", "Border Town", "Deserts"],
  "Santa Ana de la Unión": ["Urban", "Agricultural", "Rivers", "Markets", "Valleys"],
  "Juliaca": ["Urban", "Markets", "Highlands", "Lakes", "Airports", "Trade"],
  "Puno": ["Urban", "Cultural", "Historical Sites", "Lakes", "Floating Islands", "Markets"],
  "Ayacucho": ["Urban", "Cultural", "Historical Sites", "Mountains", "Festivals", "Markets"],
  "Chincha Alta": ["Urban", "Cultural", "Historical Sites", "Coastal", "Markets", "Haciendas"],
  "Huarmey": ["Urban", "Coastal", "Deserts", "Markets", "Beaches", "Archaeological Sites"],
  "Cajamarca": ["Urban", "Cultural", "Historical Sites", "Hot Springs", "Markets", "Cathedrals"],
  "Huancavelica": ["Urban", "Mountains", "Mining", "Markets", "Historical Sites", "Rivers"],
  "Ica": ["Urban", "Cultural", "Historical Sites", "Deserts", "Wineries", "Markets"],
  "Ilo": ["Urban", "Coastal", "Ports", "Markets", "Beaches", "Fishing"],
  "La Oroya": ["Urban", "Mountains", "Mining", "Rivers", "Markets", "Industrial"],
  "Nazca": ["Urban", "Deserts", "Archaeological Sites", "Lines", "Markets", "Valleys"],
  "Paita": ["Urban", "Coastal", "Ports", "Markets", "Beaches", "Fishing"],
  "Puerto Maldonado": ["Urban", "Rivers", "Jungle", "Markets", "Forests", "Wildlife"],
  "Pucón": ["Wait, that's Chile. Skip."],
  "Tarapoto": ["Urban", "Rivers", "Jungle", "Markets", "Waterfalls", "Forests"],
  "Tumbes": ["Urban", "Coastal", "Beaches", "Markets", "Mangroves", "Border Town"],
  "Ventanilla": ["Urban", "Coastal", "Industrial", "Markets", "Ports", "Suburban"],
  "Abancay": ["Urban", "Mountains", "Rivers", "Markets", "Agricultural Areas", "Canyons"],
  "Andahuaylas": ["Urban", "Highlands", "Markets", "Mountains", "Agricultural", "Festivals"]
}