{
  "Dubai": ["Urban", "Cultural", "Historical Sites", "Beaches", "Deserts", "Skyscrapers", "Shopping Malls"],
  "Abu Dhabi": ["Urban", "Cultural", "Historical Sites", "Beaches", "Deserts", "Mosques", "Museums"],
  "Sharjah": ["Urban", "Cultural", "Historical Sites", "Museums", "Parks", "Beaches"],
  "Al Ain": ["Oases", "Mountains", "Historical Sites", "Forts", "Zoos", "Archaeological Parks"],
  "Ajman": ["Beaches", "Cultural", "Historical Sites", "Mangroves", "Ports"],
  "Ras Al Khaimah": ["Mountains", "Beaches", "Historical Sites", "Forts", "Hot Springs"],
  "Fujairah": ["Beaches", "Mountains", "Historical Sites", "Forts", "Wadis"],
  "Umm Al Quwain": ["Beaches", "Historical Sites", "Forts", "Mangroves", "Islands"],
  "Kalba": ["Mangroves", "Beaches", "Historical Sites", "Forts", "Bird Sanctuaries"],
  "Dibba Al-Fujairah": ["Beaches", "Mountains", "Historical Sites", "Diving Sites"],
  "Madinat Zayed": ["Deserts", "Oases", "Historical Sites", "Shopping", "Parks"],
  "Khor Fakkan": ["Beaches", "Mountains", "Waterfalls", "Amphitheaters", "Diving"],
  "Al Dhannah": ["Beaches", "Deserts", "Mangroves", "Ports", "Industrial"],
  "Ghayathi": ["Deserts", "Oases", "Farms", "Parks", "Aqua Parks"],
  "Dhaid": ["Historical Sites", "Forts", "Oases", "Parks"],
  "Jebel Ali": ["Ports", "Beaches", "Industrial", "Free Zones", "Golf"],
  "Liwa Oasis": ["Deserts", "Oases", "Dunes", "Forts", "Palms"],
  "Hatta": ["Mountains", "Dams", "Wadis", "Heritage Villages", "Adventure Parks"],
  "Ar-Rams": ["Beaches", "Islands", "Fishing Villages", "Bird Watching"],
  "Dibba Al-Hisn": ["Beaches", "Forts", "Historical Sites", "Diving"],
  "Al Jazirah Al Hamra": ["Ghost Towns", "Historical Villages", "Beaches", "Forts"],
  "Abu al Abyad": ["Islands", "Beaches", "Mangroves", "Bird Watching"],
  "Adhen": ["Mountains", "Wadis", "Hiking Trails"],
  "Al Ajban": ["Farms", "Deserts", "Oases"],
  "Al Aryam": ["Islands", "Beaches", "Horse Shows"],
  "Al Awir": ["Markets", "Farms", "Deserts"],
  "Al Badiyah": ["Mosques", "Historical Sites", "Beaches"],
  "Al Bataeh": ["Parks", "Deserts", "Football Clubs"],
  "Al Bithnah": ["Forts", "Wadis", "Mountains"],
  "Al Faqa": ["Mountains", "Border Areas", "Hiking"],
  "Al Halah": ["Wadis", "Mountains", "Hiking Trails"],
  "Al Hamraniyah": ["Bird Watching", "Deserts"],
  "Al Hamriyah": ["Beaches", "Lagoon", "Fishing"],
  "Al Jeer": ["Ports", "Marinas", "Beaches"],
  "Al Khawaneej": ["Parks", "Quranic Gardens", "Cycling Tracks"],
  "Al Lisaili": ["Deserts", "Camel Racing", "Safaris"],
  "Al Madam": ["Ghost Towns", "Dunes", "Deserts"],
  "Al Manama": ["Forts", "Mountains", "Oases"],
  "Al Mirfa": ["Beaches", "Ports", "Power Plants"],
  "Al Qusaidat": ["Hospitals", "Public Works"],
  "Al Qor": ["Archaeological Sites", "Wadis"],
  "Al Salamah": ["Beaches", "Camping"],
  "Al Shuwaib": ["Dams", "Wadis"],
  "Al Rafaah": ["Beaches", "Camping"],
  "Al Rashidya": ["Parks", "Mosques", "Metro Stations"],
  "Al Ruwayyah": ["Stables", "Horse Riding"],
  "Al Yahar": ["Farms", "Mountains"],
  "Asimah": ["Wadis", "Hiking", "Mountains"],
  "Dalma": ["Islands", "Archaeological Sites", "Biosphere Reserves"],
  "Dadna": ["Beaches", "Mountains"],
  "Digdaga": ["Camel Racing", "Deserts"],
  "Falaj Al Mualla": ["Forts", "Oases", "Watchtowers"],
  "Ghalilah": ["Hot Springs", "Hiking Trails"],
  "Ghayl": ["Forts", "Birds of Prey Centre"],
  "Ghub": ["Oases", "Farms"],
  "Habshan": ["Oil Fields", "Deserts"],
  "Huwaylat": ["Archaeological Tombs"],
  "Khatt": ["Hot Springs", "Historical Sites"],
  "Khor Khwair": ["Industrial Zones", "Quarries"],
  "Lahbab": ["Deserts", "Dune Bashing", "Red Dunes"],
  "Marawah": ["Islands", "Biosphere Reserves", "Archaeological Sites"],
  "Masafi": ["Markets", "Forts", "Mountains"],
  "Masfut": ["Mountains", "Farms", "Marble"],
  "Mirbah": ["Beaches", "Forts"],
  "Mleiha": ["Archaeological Sites", "Deserts", "Fossil Rocks"],
  "Nahil": ["Farms", "Oases"],
  "Qidfa": ["Oases", "Power Plants", "Tombs"],
  "Sha'am": ["Forts", "Oases"],
  "Sila": ["Deserts", "Beaches", "Historical Sites"],
  "Sweihan": ["Deserts", "Solar Plants", "Camel Racing"],
  "Wadi Shah": ["Hiking Trails", "Mountains", "Pools"],
  "Zubarah": ["Archaeological Sites", "Forts", "UNESCO Sites"]
}